{
  "updated_at": "2026-07-12T11:11:45.907841",
  "events": [
    {
      "title": "Kamas Library Classic Cinema Series",
      "date": "2026-07-16",
      "description": "The Kamas Library Classic Cinema Series presents a free screening on July 16 of John Ford\u2019s landmark Western \u201cStagecoach.\u201d With Utah\u2019s Monument Valley as a back",
      "location": "Kamas Library, 110 North Main Street, Kamas, UT 84036, USA",
      "link": "https://tockify.com/kpcwcommunitycalendar/detail/1585/1783900800000",
      "source": "KPCW Community Calendar",
      "source_url": "https://www.kpcw.org/kpcw-community-calendar",
      "lat": 40.64531789999999,
      "lng": -111.2804533,
      "categories": [
        "Film",
        "Education"
      ]
    },
    {
      "title": "11th Annual TedFest - July 17-19, 2026",
      "date": "2026-07-17",
      "description": "The 11th Annual TedFest is July 17 to 19 for two full days of music in Wallsburg, Utah, west of Heber City. The festival will feature Bluegrass, Celtic, Folk, a",
      "location": "Wallsburg, Wallsburg, UT 84082, USA",
      "link": "https://tockify.com/kpcwcommunitycalendar/detail/1542/1784300400000",
      "source": "KPCW Community Calendar",
      "source_url": "https://www.kpcw.org/kpcw-community-calendar",
      "start_time": "9:00 AM",
      "end_time": "10:00 PM",
      "lat": 40.3877164,
      "lng": -111.4227333,
      "categories": [
        "Music",
        "Family",
        "Kids",
        "Festival"
      ]
    }
  ]
}