{
  "generated_at": "2026-07-03T12:26:48.324736",
  "audit_date": "2026-07-03",
  "reports": [
    {
      "city": "park-city",
      "before_count": 1793,
      "passes": {
        "past_dates": {
          "fixed": 3,
          "examples": [
            {
              "title": "Running with Ed 2026",
              "date": "2026-05-16"
            },
            {
              "title": "Park City Trail Series \u2014 5K",
              "date": "2026-06-06"
            },
            {
              "title": "Triple Trail Challenge \u2014 Round Valley Rambler & Jupiter Peak",
              "date": "2026-06-13"
            }
          ]
        },
        "absurd_spans": {
          "fixed": 4,
          "examples": [
            {
              "title": "Clases de Ingl\u00e9s para Adultos / English Classes for Adults (ESL)",
              "had_span": 55
            },
            {
              "title": "Fascia Rolling Class",
              "had_span": 181
            },
            {
              "title": "Group Fitness Classes",
              "had_span": 181
            },
            {
              "title": "Moose on the Loose Kids Trail Series",
              "had_span": 57
            }
          ]
        },
        "multi_day_splits": {
          "fixed": 6,
          "examples": [
            {
              "title": "Fox US Open of Mountain Biking",
              "original_span": "2026-09-11 to 2026-09-13",
              "split_into": [
                "2026-09-11",
                "2026-09-12",
                "2026-09-13"
              ]
            },
            {
              "title": "Chef Sarah Glover Weekend",
              "original_span": "2026-07-11 to 2026-07-12",
              "split_into": [
                "2026-07-11",
                "2026-07-12"
              ]
            },
            {
              "title": "Matilda & Gozney Weekend",
              "original_span": "2026-07-18 to 2026-07-19",
              "split_into": [
                "2026-07-18",
                "2026-07-19"
              ]
            },
            {
              "title": "Chef Ryan Arensdorf Weekend",
              "original_span": "2026-08-01 to 2026-08-02",
              "split_into": [
                "2026-08-01",
                "2026-08-02"
              ]
            },
            {
              "title": "Chef Ryan Arensdorf Weekend",
              "original_span": "2026-08-08 to 2026-08-09",
              "split_into": [
                "2026-08-08",
                "2026-08-09"
              ]
            }
          ]
        },
        "missing_end_times": {
          "fixed": 6,
          "examples": [
            {
              "title": "Concerts on the Slopes",
              "start_time": "7:00 PM",
              "new_end_time": "10:00 PM",
              "duration_hours": 3
            },
            {
              "title": "Haydn, Mendelssohn, & A Viola Concerto",
              "start_time": "8:00 PM",
              "new_end_time": "11:00 PM",
              "duration_hours": 3
            },
            {
              "title": "Concerts on the Slopes",
              "start_time": "7:00 PM",
              "new_end_time": "10:00 PM",
              "duration_hours": 3
            },
            {
              "title": "Concerts on the Slopes",
              "start_time": "7:00 PM",
              "new_end_time": "10:00 PM",
              "duration_hours": 3
            },
            {
              "title": "Concerts on the Slopes",
              "start_time": "6:00 PM",
              "new_end_time": "9:00 PM",
              "duration_hours": 3
            }
          ]
        },
        "classification": {
          "fixed": 402,
          "examples": [
            {
              "title": "Challenge Accepted!",
              "before": [],
              "after": [
                "Community"
              ]
            },
            {
              "title": "Forum Fest at Canyons Village",
              "before": [],
              "after": [
                "Festival"
              ]
            },
            {
              "title": "Old Town walking tour",
              "before": [],
              "after": [
                "Community"
              ]
            },
            {
              "title": "Bilingual Family Storytime | Hora de Cuentos Biling\u00fces en Familia",
              "before": [
                "Community"
              ],
              "after": [
                "Community",
                "Kids",
                "Education"
              ]
            },
            {
              "title": "Coffee Chat with the CEO",
              "before": [
                "Community"
              ],
              "after": [
                "Community",
                "Education"
              ]
            }
          ]
        }
      },
      "after_count": 1797,
      "total_fixes": 421
    },
    {
      "city": "elkhart-lake",
      "before_count": 196,
      "passes": {
        "past_dates": {
          "fixed": 0,
          "examples": []
        },
        "absurd_spans": {
          "fixed": 0,
          "examples": []
        },
        "multi_day_splits": {
          "fixed": 2,
          "examples": [
            {
              "title": "WeatherTech Vintage Weekend with Brian Redman",
              "original_span": "2026-07-16 to 2026-07-19",
              "split_into": [
                "2026-07-16",
                "2026-07-17",
                "2026-07-18",
                "2026-07-19"
              ]
            },
            {
              "title": "GT World Challenge America",
              "original_span": "2026-08-28 to 2026-08-30",
              "split_into": [
                "2026-08-28",
                "2026-08-29",
                "2026-08-30"
              ]
            }
          ]
        },
        "missing_end_times": {
          "fixed": 0,
          "examples": []
        },
        "classification": {
          "fixed": 0,
          "examples": []
        }
      },
      "after_count": 201,
      "total_fixes": 2
    },
    {
      "city": "heber",
      "before_count": 231,
      "passes": {
        "past_dates": {
          "fixed": 42,
          "examples": [
            {
              "title": "Midway Art Gallery Open House",
              "date": "2026-06-19"
            },
            {
              "title": "Sunrise Yoga Flow @ Grand Hyatt Deer Valley",
              "date": "2026-06-15"
            },
            {
              "title": "Ritual Chocolate Public Tour and Mini Tasting",
              "date": "2026-06-19"
            },
            {
              "title": "Anna's European Antiques Pop-Up Event",
              "date": "2026-06-26"
            },
            {
              "title": "Meet the Cows - Dairy Farm Tour",
              "date": "2026-06-15"
            }
          ]
        },
        "absurd_spans": {
          "fixed": 2,
          "examples": [
            {
              "title": "Saturday Sunset Music Series @ Heber City Main Street Park",
              "had_span": 103
            },
            {
              "title": "Saturday Sunset Music Series",
              "had_span": 180
            }
          ]
        },
        "multi_day_splits": {
          "fixed": 2,
          "examples": [
            {
              "title": "American Indian Services Native Market Days",
              "original_span": "2026-07-10 to 2026-07-12",
              "split_into": [
                "2026-07-10",
                "2026-07-11"
              ]
            },
            {
              "title": "2-Day Throwing Large Forms on the Wheel",
              "original_span": "2026-07-18 to 2026-07-19",
              "split_into": [
                "2026-07-18",
                "2026-07-19"
              ]
            }
          ]
        },
        "missing_end_times": {
          "fixed": 7,
          "examples": [
            {
              "title": "Heber Valley Chamber Golf Tournament",
              "start_time": "8:00 AM",
              "new_end_time": "9:00 AM",
              "duration_hours": 1
            },
            {
              "title": "Movie in  the Park",
              "start_time": "9:30 PM",
              "new_end_time": "11:30 PM",
              "duration_hours": 2
            },
            {
              "title": "Mountain Valley Stampede Rodeo",
              "start_time": "7:30 PM",
              "new_end_time": "9:30 PM",
              "duration_hours": 2
            },
            {
              "title": "Mountain Valley Stampede Rodeo",
              "start_time": "7:30 PM",
              "new_end_time": "9:30 PM",
              "duration_hours": 2
            },
            {
              "title": "Wilderness Circuit Finals Rodeo Friday Nov. 6th at 7:30 pm",
              "start_time": "7:30 PM",
              "new_end_time": "9:30 PM",
              "duration_hours": 2
            }
          ]
        },
        "classification": {
          "fixed": 7,
          "examples": [
            {
              "title": "Oakley PRCA Rodeo",
              "before": [],
              "after": [
                "Food & Drink",
                "Sports",
                "Kids",
                "Family",
                "Festival",
                "Community"
              ]
            },
            {
              "title": "Oakley PRCA Rodeo",
              "before": [],
              "after": [
                "Food & Drink",
                "Sports",
                "Kids",
                "Family",
                "Festival",
                "Community"
              ]
            },
            {
              "title": "Xtreme Bulls \u2014 Presented by Grade Tech",
              "before": [],
              "after": [
                "Sports"
              ]
            },
            {
              "title": "Oakley Kids Fun Run 1k & 5k",
              "before": [],
              "after": [
                "Kids"
              ]
            },
            {
              "title": "Oakley July 4th Parade",
              "before": [],
              "after": [
                "Family"
              ]
            }
          ]
        }
      },
      "after_count": 191,
      "total_fixes": 60
    },
    {
      "city": "jackson",
      "before_count": 674,
      "passes": {
        "past_dates": {
          "fixed": 0,
          "examples": []
        },
        "absurd_spans": {
          "fixed": 2,
          "examples": [
            {
              "title": "Historic Downtown Walking Tour",
              "had_span": 92
            },
            {
              "title": "Indigenous Arts and Cultural Demonstration Program Speaker Series",
              "had_span": 79
            }
          ]
        },
        "multi_day_splits": {
          "fixed": 8,
          "examples": [
            {
              "title": "Teton Mountain Runs 50K, 30K, 15K",
              "original_span": "2026-07-11 to 2026-07-12",
              "split_into": [
                "2026-07-11",
                "2026-07-12"
              ]
            },
            {
              "title": "Kids Yoga & Mindfulness Summer Camp",
              "original_span": "2026-07-13 to 2026-07-17",
              "split_into": [
                "2026-07-13",
                "2026-07-14",
                "2026-07-15",
                "2026-07-16",
                "2026-07-17"
              ]
            },
            {
              "title": "Mata Ortiz Pop-Up Pottery Shop",
              "original_span": "2026-07-17 to 2026-07-19",
              "split_into": [
                "2026-07-17",
                "2026-07-18",
                "2026-07-19"
              ]
            },
            {
              "title": "Rodeo Tent Sale",
              "original_span": "2026-07-24 to 2026-07-26",
              "split_into": [
                "2026-07-25",
                "2026-07-26"
              ]
            },
            {
              "title": "Kids Yoga & Mindfulness Summer Camp",
              "original_span": "2026-08-10 to 2026-08-14",
              "split_into": [
                "2026-08-10",
                "2026-08-11",
                "2026-08-12",
                "2026-08-13",
                "2026-08-14"
              ]
            }
          ]
        },
        "missing_end_times": {
          "fixed": 14,
          "examples": [
            {
              "title": "Karaoke at The Virginian Saloon",
              "start_time": "8:00 PM",
              "new_end_time": "11:00 PM",
              "duration_hours": 3
            },
            {
              "title": "Little Wings Story Time",
              "start_time": "11:00 AM",
              "new_end_time": "11:30 AM",
              "duration_hours": 0.5
            },
            {
              "title": "Red, White and Tunes Friday Show",
              "start_time": "6:00 PM",
              "new_end_time": "8:00 PM",
              "duration_hours": 2
            },
            {
              "title": "Red, White and Tunes Saturday Show",
              "start_time": "6:00 PM",
              "new_end_time": "8:00 PM",
              "duration_hours": 2
            },
            {
              "title": "Red, White and Tunes Sunday Show",
              "start_time": "5:00 PM",
              "new_end_time": "7:00 PM",
              "duration_hours": 2
            }
          ]
        },
        "classification": {
          "fixed": 0,
          "examples": []
        }
      },
      "after_count": 705,
      "total_fixes": 24
    }
  ]
}